{
  "bridge_name": "omega_xposed_nfcgate_bridge",
  "bridge_version": "1.0.0",
  "created_at": "2026-01-06T10:28:02.150825",
  "integration_type": "xposed_nfc_enhancement",
  "capabilities": {
    "hce_payment_services": {
      "description": "HCE (Host Card Emulation) payment services",
      "xposed_modules": [
        "NFCGate_HCE_Enabler",
        "VirtualCard_Emulator",
        "Payment_Protocol_Handler"
      ],
      "nfcgate_commands": [
        "CONFIGURE_HCE_SERVICE",
        "START_HCE_EMULATION",
        "STOP_HCE_EMULATION",
        "PROCESS_PAYMENT"
      ],
      "features": [
        "Virtual card emulation",
        "Payment protocol handling",
        "Transaction processing",
        "Security bypass"
      ]
    },
    "advanced_nfc_hooks": {
      "description": "Advanced NFC stack hooking",
      "xposed_modules": [
        "NFC_Stack_Hooker",
        "System_API_Interceptor",
        "Privilege_Escalation"
      ],
      "nfcgate_commands": [
        "HOOK_NFC_STACK",
        "INTERCEPT_NFC_CALLS",
        "BYPASS_NFC_SECURITY",
        "MODIFY_NFC_RESPONSES"
      ],
      "features": [
        "Low-level NFC stack access",
        "System API interception",
        "Privilege escalation",
        "Response modification"
      ]
    },
    "protocol_manipulation": {
      "description": "Real-time NFC protocol manipulation",
      "xposed_modules": [
        "Protocol_Modifier",
        "Data_Injection_Engine",
        "Response_Interceptor"
      ],
      "nfcgate_commands": [
        "MODIFY_NFC_PROTOCOL",
        "INJECT_NFC_DATA",
        "ALTER_RESPONSE_DATA",
        "BYPASS_PROTOCOL_VALIDATION"
      ],
      "features": [
        "Protocol modification",
        "Data injection",
        "Response alteration",
        "Validation bypass"
      ]
    }
  },
  "integration_workflow": {
    "setup": [
      "Install required Xposed modules",
      "Configure module parameters",
      "Enable module dependencies",
      "Restart Xposed framework"
    ],
    "operation": [
      "Start NFCGate service",
      "Initialize Xposed hooks",
      "Configure HCE parameters",
      "Begin NFC operations",
      "Monitor and analyze results"
    ],
    "cleanup": [
      "Disable Xposed hooks",
      "Stop NFCGate service",
      "Clear temporary data",
      "Reset system state"
    ]
  },
  "security_considerations": {
    "requirements": [
      "Root access for Xposed installation",
      "Magisk for SafetyNet bypass",
      "Module signature verification",
      "Secure storage for sensitive data"
    ],
    "risks": [
      "SafetyNet detection",
      "Bootloop risk with incompatible modules",
      "Security vulnerabilities from unsigned modules",
      "Performance impact from excessive hooking"
    ],
    "mitigations": [
      "Use MagiskHide for SafetyNet",
      "Test modules before deployment",
      "Verify module signatures",
      "Monitor system performance"
    ]
  }
}